evacuator/VERSION
evacuator/__init__.py
evacuator/core.py
evacuator/exception.py
evacuator/py.typed
evacuator/version.py
evacuator-1.0.4.dist-info/LICENSE.txt
evacuator-1.0.4.dist-info/METADATA
evacuator-1.0.4.dist-info/WHEEL
evacuator-1.0.4.dist-info/entry_points.txt
evacuator-1.0.4.dist-info/top_level.txt
evacuator-1.0.4.dist-info/RECORD
