Metadata-Version: 2.1
Name: evacuator
Version: 1.0.4
Summary: Catch an exception and exit with an exit code
Home-page: https://github.com/MobileTeleSystems/evacuator
Author: DataOps.ETL
Author-email: onetools@mts.ru
License: Apache-2.0
Project-URL: Documentation, https://evacuator.readthedocs.io
Project-URL: Source, https://github.com/MobileTeleSystems/evacuator
Project-URL: CI/CD, https://github.com/MobileTeleSystems/evacuator/actions
Project-URL: Tracker, https://github.com/MobileTeleSystems/evacuator/issues
Classifier: Development Status :: 4 - Beta
Classifier: Intended Audience :: Developers
Classifier: License :: OSI Approved :: Apache Software License
Classifier: Operating System :: OS Independent
Classifier: Programming Language :: Python :: 3 :: Only
Classifier: Programming Language :: Python :: 3.7
Classifier: Programming Language :: Python :: 3.8
Classifier: Programming Language :: Python :: 3.9
Classifier: Programming Language :: Python :: 3.10
Classifier: Programming Language :: Python :: 3.11
Classifier: Programming Language :: Python :: 3.12
Classifier: Typing :: Typed
Requires-Python: >=3.7
License-File: LICENSE.txt
